[
  {
    "customerId": "CUST26503154",
    "username": "test_user",
    "password": "password123",
    "firstName": "Test",
    "lastName": "User",
    "dob": "1990-01-01",
    "gender": "M",
    "accountType": "Pride",
    "accountNumber": "562107162630",
    "balance": 50000,
    "transactions": [],
    "failedAttempts": 0,
    "locked": false,
    "pendingAmbFees": 0.0,
    "recurringBills": [],
    "salaryProfile": null,
    "cards": []
  },
  {
    "customerId": "CUST17385053",
    "username": "test_user",
    "password": "password123",
    "firstName": "Test",
    "lastName": "User",
    "dob": "1990-01-01",
    "gender": "M",
    "accountType": "Pride",
    "accountNumber": "562106510050",
    "balance": 50000,
    "transactions": [],
    "failedAttempts": 0,
    "locked": false,
    "pendingAmbFees": 0.0,
    "recurringBills": [],
    "salaryProfile": null,
    "cards": [
      {
        "cardId": "CARD185405944",
        "cardNumber": "4506229247228493",
        "customerId": "CUST17385053",
        "accountNumber": "562106510050",
        "cardType": "CREDIT",
        "network": "VISA",
        "expiryDate": "2029-12-01",
        "cvv": "034",
        "blocked": false,
        "dailyLimit": 50000.0,
        "creditLimit": 100000,
        "creditUsed": 0.0,
        "billingDay": 1,
        "lastBillDate": null,
        "dueDate": null,
        "outstandingBalance": 0.0,
        "minimumDue": 0.0,
        "interestRate": 0.18,
        "rewardPoints": 0.0,
        "rewardRate": 0.01,
        "autoPayPolicy": "NONE"
      }
    ]
  },
  {
    "customerId": "CUST82447457",
    "username": "test_user",
    "password": "password123",
    "firstName": "Test",
    "lastName": "User",
    "dob": "1990-01-01",
    "gender": "M",
    "accountType": "Pride",
    "accountNumber": "562128937420",
    "balance": 50000,
    "transactions": [],
    "failedAttempts": 0,
    "locked": false,
    "pendingAmbFees": 0.0,
    "recurringBills": [],
    "salaryProfile": null,
    "cards": [
      {
        "cardId": "CARD432793834",
        "cardNumber": "4506223895491222",
        "customerId": "CUST82447457",
        "accountNumber": "562128937420",
        "cardType": "CREDIT",
        "network": "VISA",
        "expiryDate": "2029-12-01",
        "cvv": "271",
        "blocked": false,
        "dailyLimit": 50000.0,
        "creditLimit": 100000,
        "creditUsed": 0.0,
        "billingDay": 1,
        "lastBillDate": null,
        "dueDate": null,
        "outstandingBalance": 0.0,
        "minimumDue": 0.0,
        "interestRate": 0.18,
        "rewardPoints": 0.0,
        "rewardRate": 0.01,
        "autoPayPolicy": "NONE"
      }
    ]
  },
  {
    "customerId": "CUST02580696",
    "username": "test_user",
    "password": "password123",
    "firstName": "Test",
    "lastName": "User",
    "dob": "1990-01-01",
    "gender": "M",
    "accountType": "Pride",
    "accountNumber": "562194343303",
    "balance": 50000,
    "transactions": [
      {
        "id": "FHIC9106346783",
        "type": "CREDIT_CARD_BILL_PAYMENT",
        "amount": 0,
        "resultingBalance": 50000,
        "timestamp": "03-09-2025 21:50:31",
        "chequeId": null,
        "category": null,
        "merchant": null,
        "paymentMethod": null,
        "metadata": {
          "bill_id": "BILL1001",
          "bill_name": "Internet Bill",
          "nach_id": "NACH20251202323445",
          "payment_method": "credit_card",
          "card_id": "CARD134318507",
          "card_network": "VISA",
          "reward_points_earned": 9,
          "bill_amount": 908.8
        }
      }
    ],
    "failedAttempts": 0,
    "locked": false,
    "pendingAmbFees": 0.0,
    "recurringBills": [],
    "salaryProfile": null,
    "cards": [
      {
        "cardId": "CARD134318507",
        "cardNumber": "4506220053786823",
        "customerId": "CUST02580696",
        "accountNumber": "562194343303",
        "cardType": "CREDIT",
        "network": "VISA",
        "expiryDate": "2029-12-01",
        "cvv": "682",
        "blocked": false,
        "dailyLimit": 50000.0,
        "creditLimit": 100000,
        "creditUsed": 1023.756462697815,
        "billingDay": 1,
        "lastBillDate": "2025-12-01",
        "dueDate": "2025-12-16",
        "outstandingBalance": 1023.756462697815,
        "minimumDue": 500.0,
        "interestRate": 0.18,
        "rewardPoints": 9.0,
        "rewardRate": 0.01,
        "autoPayPolicy": "NONE"
      }
    ]
  },
  {
    "customerId": "CUST50447979",
    "username": "test_user",
    "password": "password123",
    "firstName": "Test",
    "lastName": "User",
    "dob": "1990-01-01",
    "gender": "M",
    "accountType": "Pride",
    "accountNumber": "562155743506",
    "balance": 50000,
    "transactions": [
      {
        "id": "FHIC8410318586",
        "type": "CREDIT_CARD_BILL_PAYMENT",
        "amount": 0,
        "resultingBalance": 50000,
        "timestamp": "03-09-2025 21:50:31",
        "chequeId": null,
        "category": null,
        "merchant": null,
        "paymentMethod": null,
        "metadata": {
          "bill_id": "BILL1001",
          "bill_name": "Internet Bill",
          "nach_id": "NACH20251202993581",
          "payment_method": "credit_card",
          "card_id": "CARD644879925",
          "card_network": "VISA",
          "reward_points_earned": 9,
          "bill_amount": 953.49
        }
      }
    ],
    "failedAttempts": 0,
    "locked": false,
    "pendingAmbFees": 0.0,
    "recurringBills": [],
    "salaryProfile": null,
    "cards": [
      {
        "cardId": "CARD644879925",
        "cardNumber": "4506225853979239",
        "customerId": "CUST50447979",
        "accountNumber": "562155743506",
        "cardType": "CREDIT",
        "network": "VISA",
        "expiryDate": "2029-12-01",
        "cvv": "040",
        "blocked": false,
        "dailyLimit": 50000.0,
        "creditLimit": 100000,
        "creditUsed": 1074.0994163927594,
        "billingDay": 1,
        "lastBillDate": "2025-12-01",
        "dueDate": "2025-12-16",
        "outstandingBalance": 1074.0994163927594,
        "minimumDue": 500.0,
        "interestRate": 0.18,
        "rewardPoints": 9.0,
        "rewardRate": 0.01,
        "autoPayPolicy": "NONE"
      }
    ]
  },
  {
    "customerId": "CUST63758757",
    "username": "test_user",
    "password": "password123",
    "firstName": "Test",
    "lastName": "User",
    "dob": "1990-01-01",
    "gender": "M",
    "accountType": "Pride",
    "accountNumber": "562175592508",
    "balance": 50000,
    "transactions": [
      {
        "id": "FHIC6187448410",
        "type": "CREDIT_CARD_BILL_PAYMENT",
        "amount": 0,
        "resultingBalance": 50000,
        "timestamp": "03-09-2025 21:50:31",
        "chequeId": null,
        "category": null,
        "merchant": null,
        "paymentMethod": null,
        "metadata": {
          "bill_id": "BILL1001",
          "bill_name": "Internet Bill",
          "nach_id": "NACH20251202767828",
          "payment_method": "credit_card",
          "card_id": "CARD633615970",
          "card_network": "VISA",
          "reward_points_earned": 10,
          "bill_amount": 1067.77
        }
      }
    ],
    "failedAttempts": 0,
    "locked": false,
    "pendingAmbFees": 0.0,
    "recurringBills": [],
    "salaryProfile": null,
    "cards": [
      {
        "cardId": "CARD633615970",
        "cardNumber": "4506226170146429",
        "customerId": "CUST63758757",
        "accountNumber": "562175592508",
        "cardType": "CREDIT",
        "network": "VISA",
        "expiryDate": "2029-12-01",
        "cvv": "498",
        "blocked": false,
        "dailyLimit": 50000.0,
        "creditLimit": 100000,
        "creditUsed": 1202.8349891888708,
        "billingDay": 1,
        "lastBillDate": "2025-12-01",
        "dueDate": "2025-12-16",
        "outstandingBalance": 1202.8349891888708,
        "minimumDue": 500.0,
        "interestRate": 0.18,
        "rewardPoints": 10.0,
        "rewardRate": 0.01,
        "autoPayPolicy": "NONE"
      }
    ]
  }
]